[
  {
    "text": "退休特工父亲传授女儿“保命心法”：不管在哪，永远别背对着门坐",
    "href": "https://www.toutiao.com/article/7582954326130999843/",
    "type": "article"
  },
  {
    "text": "刚说完“要丢东西”手机就没？泰国算命大师亲手偷走女孩的手机！",
    "href": "https://www.toutiao.com/article/7590816140264309294/",
    "type": "article"
  },
  {
    "text": "全球纯电第一换人：比亚迪超特斯拉60万辆，2026年买车先算3笔账",
    "href": "https://www.toutiao.com/article/7590798696405615167/",
    "type": "article"
  },
  {
    "text": "雅加达公交换电提速：为何中国电动大巴在东南亚落地更快",
    "href": "https://www.toutiao.com/w/1853141641902089/",
    "type": "weitoutiao"
  },
  {
    "text": "雅加达公交换电提速：为何中国电动大巴在东南亚落地更快",
    "href": "https://www.toutiao.com/article/7590463146972824106/",
    "type": "article"
  },
  {
    "text": "小时候抢着放烟花，长大后烟花没变，变的是“一起看的人”少了",
    "href": "https://www.toutiao.com/w/1853137716802572/",
    "type": "weitoutiao"
  },
  {
    "text": "小时候抢着放烟花，长大后烟花没变，变的是“一起看的人”少了",
    "href": "https://www.toutiao.com/article/7590450705698226694/",
    "type": "article"
  },
  {
    "text": "2026：风险开始“平民化”，你会在工作和生活里先感觉到",
    "href": "https://www.toutiao.com/w/1853136256057355/",
    "type": "weitoutiao"
  },
  {
    "text": "2026：风险开始“平民化”，你会在工作和生活里先感觉到",
    "href": "https://www.toutiao.com/article/7590442364309652011/",
    "type": "article"
  },
  {
    "text": "从今天开始：把未来的你，写进每一次选择里",
    "href": "https://www.toutiao.com/w/1853133922913280/",
    "type": "weitoutiao"
  },
  {
    "text": "从今天开始：把未来的你，写进每一次选择里",
    "href": "https://www.toutiao.com/article/7590434965976777279/",
    "type": "article"
  },
  {
    "text": "我用手机记买菜清单3个月，发现一个坑：更方便，但更容易乱买",
    "href": "https://www.toutiao.com/w/1853044507087879/",
    "type": "weitoutiao"
  },
  {
    "text": "我用手机记买菜清单3个月，发现一个坑：更方便，但更容易乱买",
    "href": "https://www.toutiao.com/article/7590068907390648867/",
    "type": "article"
  },
  {
    "text": "很多婚姻不是败给不爱了，而是败给一句话：\n“当初婚礼都办这么大了，你现在跟我计较...",
    "href": "https://www.toutiao.com/w/1853043315904524/",
    "type": "weitoutiao"
  },
  {
    "text": "研究3000对夫妻发现，婚礼越豪华，离婚风险反而越高？",
    "href": "https://www.toutiao.com/w/1853042410034312/",
    "type": "weitoutiao"
  },
  {
    "text": "研究3000对夫妻发现，婚礼越豪华，离婚风险反而越高？",
    "href": "https://www.toutiao.com/article/7590058751202165283/",
    "type": "article"
  },
  {
    "text": "以为是末日火山爆发？太平洋上空的“神秘红光”刷屏",
    "href": "https://www.toutiao.com/article/7589278735673672228/",
    "type": "article"
  },
  {
    "text": "吼了孩子100次都没用？美国CDC建议：换成这3句话，孩子立马听",
    "href": "https://www.toutiao.com/w/1852850146377923/",
    "type": "weitoutiao"
  },
  {
    "text": "吼了孩子100次都没用？美国CDC建议：换成这3句话，孩子立马听",
    "href": "https://www.toutiao.com/article/7589255238218711588/",
    "type": "article"
  },
  {
    "text": "你以为超速能省10分钟？多数情况只省“一首歌”",
    "href": "https://www.toutiao.com/w/1852680526709771/",
    "type": "weitoutiao"
  },
  {
    "text": "你以为超速能省10分钟？多数情况只省“一首歌”",
    "href": "https://www.toutiao.com/article/7588577569931346495/",
    "type": "article"
  },
  {
    "text": "4S店让你加钱“充氮气”，真能更安全更省油吗？结论很扎心",
    "href": "https://www.toutiao.com/w/1852679710482499/",
    "type": "weitoutiao"
  },
  {
    "text": "4S店让你加钱“充氮气”，真能更安全更省油吗？结论很扎心",
    "href": "https://www.toutiao.com/article/7588574606739489321/",
    "type": "article"
  },
  {
    "text": "攒了一辈子钱，全给儿女“埋了雷”？这些传承大坑，有房的都要看",
    "href": "https://www.toutiao.com/w/1852678754824201/",
    "type": "weitoutiao"
  },
  {
    "text": "攒了一辈子钱，全给儿女“埋了雷”？这些传承大坑，有房的都要看",
    "href": "https://www.toutiao.com/article/7588567145718563371/",
    "type": "article"
  },
  {
    "text": "退役特种兵的“5个随地动作”：5个动作，每天15分钟，人老腿不老",
    "href": "https://www.toutiao.com/w/1852676740708489/",
    "type": "weitoutiao"
  },
  {
    "text": "退役特种兵的“5个随地动作”：5个动作，每天15分钟，人老腿不老",
    "href": "https://www.toutiao.com/article/7588561707920785963/",
    "type": "article"
  },
  {
    "text": "这3道“反直觉”测试题，据说刷掉了50%的名校生？不服来测",
    "href": "https://www.toutiao.com/w/1852595991356617/",
    "type": "weitoutiao"
  },
  {
    "text": "这3道“反直觉”测试题，据说刷掉了50%的名校生？不服来测",
    "href": "https://www.toutiao.com/article/7588230302221238793/",
    "type": "article"
  },
  {
    "text": "中国人爱喝热水，外国人爱喝冰水，谁更科学？答案藏在“场景”里",
    "href": "https://www.toutiao.com/article/7588223066686128690/",
    "type": "article"
  },
  {
    "text": "警惕职场“垃圾友谊”！那个天天陪你骂领导的同事，正在废掉你",
    "href": "https://www.toutiao.com/article/7588214367330779698/",
    "type": "article"
  },
  {
    "text": "日本防卫预算再破纪录：9.04万亿日元砸向导弹与无人化",
    "href": "https://www.toutiao.com/article/7588102192918266395/",
    "type": "article"
  },
  {
    "text": "圣诞不休！美军11舰围堵委内瑞拉，特朗普下令：是隔离，不是开战",
    "href": "https://www.toutiao.com/article/7587797554465735231/",
    "type": "article"
  },
  {
    "text": "受够了伪环保？日本新发明打脸“纸吸管”：原料能吃，入海零残留",
    "href": "https://www.toutiao.com/article/7587486115016360484/",
    "type": "article"
  },
  {
    "text": "不用上班也有工资？每人都有份！马绍尔群岛全民发钱每季200美元",
    "href": "https://www.toutiao.com/article/7587472829457744390/",
    "type": "article"
  },
  {
    "text": "煮个龙虾也要坐牢？英国出台新规：活煮算虐待，厨师看懵了！",
    "href": "https://www.toutiao.com/w/1852409459279884/",
    "type": "weitoutiao"
  },
  {
    "text": "煮个龙虾也要坐牢？英国出台新规：活煮算虐待，厨师看懵了！",
    "href": "https://www.toutiao.com/article/7587457688506860073/",
    "type": "article"
  },
  {
    "text": "这十个“坑娃式”育儿潮流，真该早点结束了",
    "href": "https://www.toutiao.com/w/1852319555058819/",
    "type": "weitoutiao"
  },
  {
    "text": "这十个“坑娃式”育儿潮流，真该早点结束了",
    "href": "https://www.toutiao.com/article/7587091312214573611/",
    "type": "article"
  },
  {
    "text": "心理学家提醒：你对老婆的态度，决定了你女儿未来能嫁什么样的人",
    "href": "https://www.toutiao.com/article/7587082429429514815/",
    "type": "article"
  },
  {
    "text": "那一双塞满稻草的鞋，踩碎了谁的盛世美梦？看完我只剩迷茫",
    "href": "https://www.toutiao.com/article/7587071397320229430/",
    "type": "article"
  },
  {
    "text": "这是一个疯狂的时代：黄金和白银都在狂飙，全球经济到底怎么了？",
    "href": "https://www.toutiao.com/w/1852305644272768/",
    "type": "weitoutiao"
  },
  {
    "text": "这是一个疯狂的时代：黄金和白银都在狂飙，全球经济到底怎么了？",
    "href": "https://www.toutiao.com/article/7587041059411067398/",
    "type": "article"
  },
  {
    "text": "声波“隔空碎瘤”、免疫“唤醒人体”：看懂新疗法热潮背后的真相",
    "href": "https://www.toutiao.com/article/7587032189991518763/",
    "type": "article"
  },
  {
    "text": "千元机可能要变贵了：不是品牌飘了，是这类零件在暴涨",
    "href": "https://www.toutiao.com/w/1852295806254272/",
    "type": "weitoutiao"
  },
  {
    "text": "千元机可能要变贵了：不是品牌飘了，是这类零件在暴涨",
    "href": "https://www.toutiao.com/article/7587002046637736491/",
    "type": "article"
  },
  {
    "text": "买新能源车，几万块的“自动驾驶包”到底该不该选？",
    "href": "https://www.toutiao.com/w/1852293931803724/",
    "type": "weitoutiao"
  },
  {
    "text": "买新能源车，几万块的“自动驾驶包”到底该不该选？",
    "href": "https://www.toutiao.com/article/7586995046944342534/",
    "type": "article"
  },
  {
    "text": "别只怪老人宠孩子！研究发现：隔代带娃的“副作用”，根源在父母",
    "href": "https://www.toutiao.com/w/1852286918543368/",
    "type": "weitoutiao"
  },
  {
    "text": "别只怪老人宠孩子！研究发现：隔代带娃的“副作用”，根源在父母",
    "href": "https://www.toutiao.com/article/7586965196275565097/",
    "type": "article"
  },
  {
    "text": "非洲二八大杠传奇：只要我骑得够快，香蕉就追不上我",
    "href": "https://www.toutiao.com/article/7586675633887986195/",
    "type": "article"
  },
  {
    "text": "当玩具变成救命工具：那个被塞进手里的小哨子，刺痛了谁的心？",
    "href": "https://www.toutiao.com/article/7586657001254453801/",
    "type": "article"
  },
  {
    "text": "反扒战术手册：学会“核心区域隔离法”，让小偷把你踢出目标名单",
    "href": "https://www.toutiao.com/w/1852201720673287/",
    "type": "weitoutiao"
  },
  {
    "text": "反扒战术手册：学会“核心区域隔离法”，让小偷把你踢出目标名单",
    "href": "https://www.toutiao.com/article/7586611639164600895/",
    "type": "article"
  },
  {
    "text": "拿破仑华盛顿为何总“手插衣襟”？真相：这是古代精英的社交密码",
    "href": "https://www.toutiao.com/article/7586600666240385542/",
    "type": "article"
  },
  {
    "text": "建议收藏：利用“心理倒置”，一句话瞬间搞定孩子的“磨蹭拖拉”",
    "href": "https://www.toutiao.com/w/1852195898330371/",
    "type": "weitoutiao"
  },
  {
    "text": "建议收藏：利用“心理倒置”，一句话瞬间搞定孩子的“磨蹭拖拉”",
    "href": "https://www.toutiao.com/article/7586592479172968996/",
    "type": "article"
  },
  {
    "text": "夜空惊现“绿色巨人”极光爆发似人影，当地人的解释让人背后发凉",
    "href": "https://www.toutiao.com/w/1852062746363915/",
    "type": "weitoutiao"
  },
  {
    "text": "夜空惊现“绿色巨人”极光爆发似人影，当地人的解释让人背后发凉",
    "href": "https://www.toutiao.com/article/7586043111994884634/",
    "type": "article"
  },
  {
    "text": "为什么有人80岁能爬山，有人60岁就瘫痪？关键不在年龄",
    "href": "https://www.toutiao.com/article/7585949327664382473/",
    "type": "article"
  },
  {
    "text": "晚上洗澡其实是在“养细菌”？实验室揭秘：床单不换怎么洗都白搭",
    "href": "https://www.toutiao.com/article/7585947552999129627/",
    "type": "article"
  },
  {
    "text": "102岁神经科泰斗坦白：退休才是大脑萎缩的开始！",
    "href": "https://www.toutiao.com/article/7585935132553478702/",
    "type": "article"
  },
  {
    "text": "说好的拯救地球呢？看到中国电车崛起，他们把“环保”桌子掀了！",
    "href": "https://www.toutiao.com/w/1852018376961228/",
    "type": "weitoutiao"
  },
  {
    "text": "说好的拯救地球呢？看到中国电车崛起，他们把“环保”桌子掀了！",
    "href": "https://www.toutiao.com/article/7585865480225702450/",
    "type": "article"
  },
  {
    "text": "手机电量用完再充？这是在给电池“送终”，寿命缩短一半！",
    "href": "https://www.toutiao.com/w/1851956525757452/",
    "type": "weitoutiao"
  },
  {
    "text": "手机电量用完再充？这是在给电池“送终”，寿命缩短一半！",
    "href": "https://www.toutiao.com/article/7585611751119421995/",
    "type": "article"
  },
  {
    "text": "别再只盯着品牌看！衣服拉链上的YKK三个字，藏着大牌不说的猫腻",
    "href": "https://www.toutiao.com/article/7585609592210588196/",
    "type": "article"
  },
  {
    "text": "为什么微波炉加热时不能贴近看？那层黑网背后的物理博弈。",
    "href": "https://www.toutiao.com/article/7585606676612252166/",
    "type": "article"
  },
  {
    "text": "剩菜存放：铝箔纸竟是细菌的“温室”？这2种菜，劝你尽早停手",
    "href": "https://www.toutiao.com/w/1851952220719113/",
    "type": "weitoutiao"
  },
  {
    "text": "剩菜存放：铝箔纸竟是细菌的“温室”？这2种菜，劝你尽早停手",
    "href": "https://www.toutiao.com/article/7585587714691580479/",
    "type": "article"
  },
  {
    "text": "海南封关后，去旅游买东西真会便宜20%-30%？",
    "href": "https://www.toutiao.com/article/7585546965908210217/",
    "type": "article"
  },
  {
    "text": "为什么你越努力越穷？不是命不好，是掉进了这3个陷阱",
    "href": "https://www.toutiao.com/w/1851837938793483/",
    "type": "weitoutiao"
  },
  {
    "text": "为什么你越努力越穷？不是命不好，是掉进了这3个陷阱",
    "href": "https://www.toutiao.com/article/7585127462628016703/",
    "type": "article"
  },
  {
    "text": "总记性差？别以为只是老了！出现这7个信号，或是大脑在“求救”",
    "href": "https://www.toutiao.com/article/7585116935763837446/",
    "type": "article"
  },
  {
    "text": "总是凌晨4点“自然醒”？医生：这是身体在发“求救信号”",
    "href": "https://www.toutiao.com/article/7585110351201550891/",
    "type": "article"
  },
  {
    "text": "人这一辈子，只有躺在病床上时，才敢承认这3个真相！",
    "href": "https://www.toutiao.com/w/1851832192443468/",
    "type": "weitoutiao"
  },
  {
    "text": "人这一辈子，只有躺在病床上时，才敢承认这3个真相！",
    "href": "https://www.toutiao.com/article/7585100746224452102/",
    "type": "article"
  },
  {
    "text": "为什么老实人总吃亏？太守规矩的人，往往最早“累”垮身体！",
    "href": "https://www.toutiao.com/w/1851785135222796/",
    "type": "weitoutiao"
  },
  {
    "text": "为什么老实人总吃亏？太守规矩的人，往往最早“累”垮身体！",
    "href": "https://www.toutiao.com/article/7584910843435958824/",
    "type": "article"
  },
  {
    "text": "谁发明的？除了中国的蛇酒，这4种“阴间饮料”千万别碰",
    "href": "https://www.toutiao.com/w/1851784438928643/",
    "type": "weitoutiao"
  },
  {
    "text": "谁发明的？除了中国的蛇酒，这4种“阴间饮料”千万别碰",
    "href": "https://www.toutiao.com/article/7584907793300226560/",
    "type": "article"
  },
  {
    "text": "走路快慢暴露你的真实层次！研究发现：这就不是简单的急性子",
    "href": "https://www.toutiao.com/article/7584896379445608995/",
    "type": "article"
  },
  {
    "text": "什么是“好命”？大数据统计了3800万人的一生，发现一个惊人规律",
    "href": "https://www.toutiao.com/w/1851769574467659/",
    "type": "weitoutiao"
  },
  {
    "text": "什么是“好命”？大数据统计了3800万人的一生，发现一个惊人规律",
    "href": "https://www.toutiao.com/article/7584847057169465856/",
    "type": "article"
  },
  {
    "text": "澳洲正式封杀青少年社交账号，这会让我们的孩子更安全吗？",
    "href": "https://www.toutiao.com/article/7584835719731675663/",
    "type": "article"
  },
  {
    "text": "路遇歹徒该跑还是拼？安全专家大实话：别逞强，这4个动作能保命",
    "href": "https://www.toutiao.com/article/7584834499976921615/",
    "type": "article"
  },
  {
    "text": "为什么日子越过越好，心却越来越空？",
    "href": "https://www.toutiao.com/w/1851763042167883/",
    "type": "weitoutiao"
  },
  {
    "text": "为什么日子越过越好，心却越来越空？",
    "href": "https://www.toutiao.com/article/7584820133445583360/",
    "type": "article"
  },
  {
    "text": "那个显示乱码的深夜外卖单，送完一年多，现在想起来还不敢回头看",
    "href": "https://www.toutiao.com/w/1851700849164295/",
    "type": "weitoutiao"
  },
  {
    "text": "那个显示乱码的深夜外卖单，送完一年多，现在想起来还不敢回头看",
    "href": "https://www.toutiao.com/article/7584557168871899658/",
    "type": "article"
  },
  {
    "text": "干得快，就得给懒同事擦屁股？两个打工人的反击，一个比一个绝",
    "href": "https://www.toutiao.com/article/7584543323323433481/",
    "type": "article"
  },
  {
    "text": "谁在代表我们？揭开西方权力的面纱：你只是代价，不是主人",
    "href": "https://www.toutiao.com/article/7584041888898990607/",
    "type": "article"
  },
  {
    "text": "停止在婚姻里“讨好”吧！真正的伴侣，从来不让你拼命踮起脚尖",
    "href": "https://www.toutiao.com/w/1851561921351884/",
    "type": "weitoutiao"
  },
  {
    "text": "停止在婚姻里“讨好”吧！真正的伴侣，从来不让你拼命踮起脚尖",
    "href": "https://www.toutiao.com/article/7583995553810301455/",
    "type": "article"
  },
  {
    "text": "心理专家大实话：让你晚年痛苦的不是没钱，而是这11个“心魔”",
    "href": "https://www.toutiao.com/article/7583806690638823977/",
    "type": "article"
  },
  {
    "text": "人到中年才明白的残忍真相：越是“老实肯干”，往往混得越惨！",
    "href": "https://www.toutiao.com/article/7583804716614828586/",
    "type": "article"
  },
  {
    "text": "西方为何突然这也禁、那也查？看懂这套“强盗逻辑”，才不会吃亏",
    "href": "https://www.toutiao.com/w/1851513935512648/",
    "type": "weitoutiao"
  },
  {
    "text": "西方为何突然这也禁、那也查？看懂这套“强盗逻辑”，才不会吃亏",
    "href": "https://www.toutiao.com/article/7583795696671752710/",
    "type": "article"
  },
  {
    "text": "身家过亿就幸福了？顶级顾问坦白：深夜里，这些富人最怕3件事",
    "href": "https://www.toutiao.com/w/1851511162863624/",
    "type": "weitoutiao"
  },
  {
    "text": "身家过亿就幸福了？顶级顾问坦白：深夜里，这些富人最怕3件事",
    "href": "https://www.toutiao.com/article/7583787511898669622/",
    "type": "article"
  },
  {
    "text": "心脏专家紧急警告：这种“零糖”饮料比糖水还伤肝，别再被骗了",
    "href": "https://www.toutiao.com/article/7583784944481223222/",
    "type": "article"
  },
  {
    "text": "曾给奥巴马挡子弹的女特工：高手都很沉默！做一件事，能看透人心",
    "href": "https://www.toutiao.com/w/1851508637367308/",
    "type": "weitoutiao"
  },
  {
    "text": "曾给奥巴马挡子弹的女特工：高手都很沉默！做一件事，能看透人心",
    "href": "https://www.toutiao.com/article/7583777157776753194/",
    "type": "article"
  },
  {
    "text": "活了3亿年熬死恐龙！专家揭秘：乌龟壳的真实用途，不是为了防身",
    "href": "https://www.toutiao.com/article/7583768501068841515/",
    "type": "article"
  },
  {
    "text": "老外俗语有多野？英国人下猫下狗，瑞典人种土豆，立陶宛人下斧头",
    "href": "https://www.toutiao.com/w/1851420017810432/",
    "type": "weitoutiao"
  },
  {
    "text": "老外俗语有多野？英国人下猫下狗，瑞典人种土豆，立陶宛人下斧头",
    "href": "https://www.toutiao.com/article/7583413692692202030/",
    "type": "article"
  },
  {
    "text": "古罗马斗兽场的隐秘真相：女角斗士为何不戴头盔？结局令人唏嘘",
    "href": "https://www.toutiao.com/w/1851396988717508/",
    "type": "weitoutiao"
  },
  {
    "text": "古罗马斗兽场的隐秘真相：女角斗士为何不戴头盔？结局令人唏嘘",
    "href": "https://www.toutiao.com/article/7583320544503464486/",
    "type": "article"
  },
  {
    "text": "若核弹真的爆炸，普通人该怎么办？切记：生死就在这黄金24小时",
    "href": "https://www.toutiao.com/w/1851388843459593/",
    "type": "weitoutiao"
  },
  {
    "text": "若核弹真的爆炸，普通人该怎么办？切记：生死就在这黄金24小时",
    "href": "https://www.toutiao.com/article/7583286116850106890/",
    "type": "article"
  },
  {
    "text": "600岁造船避难？地质学家揭秘：那场灭世洪水，可能只是局部暴雨",
    "href": "https://www.toutiao.com/article/7583281675052810795/",
    "type": "article"
  },
  {
    "text": "心理学家直言：人生的苦多半是自找的，学会这4个习惯，就顺了",
    "href": "https://www.toutiao.com/article/7583267588373774890/",
    "type": "article"
  },
  {
    "text": "你不是懒，你只是脑子里的“杂音”太多",
    "href": "https://www.toutiao.com/article/7583261679799058971/",
    "type": "article"
  },
  {
    "text": "人到中年才明白：比起假装聪明，承认“我不知道”才是顶级智慧",
    "href": "https://www.toutiao.com/w/1851380359365632/",
    "type": "weitoutiao"
  },
  {
    "text": "人到中年才明白：比起假装聪明，承认“我不知道”才是顶级智慧",
    "href": "https://www.toutiao.com/article/7583251690531324454/",
    "type": "article"
  },
  {
    "text": "德国制造神话破灭？火车晚点逼疯瑞士人，连厕所都挤不进去",
    "href": "https://www.toutiao.com/w/1851313130066956/",
    "type": "weitoutiao"
  },
  {
    "text": "德国制造神话破灭？火车晚点逼疯瑞士人，连厕所都挤不进去",
    "href": "https://www.toutiao.com/article/7582973076434993699/",
    "type": "article"
  },
  {
    "text": "退休特工父亲传授女儿“保命心法”：不管在哪，永远别背对着门坐",
    "href": "https://www.toutiao.com/w/1851309878870016/",
    "type": "weitoutiao"
  },
  {
    "text": "以前觉得热闹，现在只想清静：人变老的几个扎心迹象，全说中了",
    "href": "https://www.toutiao.com/w/1851293214240907/",
    "type": "weitoutiao"
  },
  {
    "text": "以前觉得热闹，现在只想清静：人变老的几个扎心迹象，全说中了",
    "href": "https://www.toutiao.com/article/7582893785697239604/",
    "type": "article"
  },
  {
    "text": "一个人将来有没有出息？不用看家庭背景，这21个细节早已暴露真相",
    "href": "https://www.toutiao.com/w/1851291931356356/",
    "type": "weitoutiao"
  },
  {
    "text": "一个人将来有没有出息？不用看家庭背景，这21个细节早已暴露真相",
    "href": "https://www.toutiao.com/article/7582888618633560611/",
    "type": "article"
  },
  {
    "text": "真正混得好的人，往往都很“静”：不炫耀，不合群，只做对三件事",
    "href": "https://www.toutiao.com/article/7582883046437732898/",
    "type": "article"
  },
  {
    "text": "别不信！几句话骗光养老钱，警方曝光最新“洗脑”套路，速看",
    "href": "https://www.toutiao.com/article/7582583338028843526/",
    "type": "article"
  },
  {
    "text": "走路发飘？大脑变傻前有“隐形征兆”，这杯“便宜茶”被低估了",
    "href": "https://www.toutiao.com/article/7582544264207385142/",
    "type": "article"
  },
  {
    "text": "为何胡子“野火烧不尽”，头发却“一去不复返”？",
    "href": "https://www.toutiao.com/article/7581477098049733174/",
    "type": "article"
  },
  {
    "text": "正午的食槽",
    "href": "https://www.toutiao.com/article/7581135958662234664/",
    "type": "article"
  },
  {
    "text": "婚姻和生死，看似是选择，其实大半是“命数”",
    "href": "https://www.toutiao.com/article/7580729248655098410/",
    "type": "article"
  },
  {
    "text": "人到中年才明白，你即使再善良，也会有人恨你，根源只有两个字",
    "href": "https://www.toutiao.com/w/1850751827751943/",
    "type": "weitoutiao"
  },
  {
    "text": "人到中年才明白，你即使再善良，也会有人恨你，根源只有两个字",
    "href": "https://www.toutiao.com/article/7580678055815823914/",
    "type": "article"
  },
  {
    "text": "气场是练出来的！南加大最近发现：改掉一个说话习惯，说服力翻倍",
    "href": "https://www.toutiao.com/w/1850750028150796/",
    "type": "weitoutiao"
  },
  {
    "text": "气场是练出来的！南加大最近发现：改掉一个说话习惯，说服力翻倍",
    "href": "https://www.toutiao.com/article/7580669019804516905/",
    "type": "article"
  },
  {
    "text": "为什么班里考第一的多是女生，最后当科学家的却是男生？",
    "href": "https://www.toutiao.com/article/7580664373175157311/",
    "type": "article"
  },
  {
    "text": "为什么炉子上烧水咕嘟冒泡，微波炉里却死一般的安静？",
    "href": "https://www.toutiao.com/article/7580434500442653236/",
    "type": "article"
  },
  {
    "text": "紧急提醒：今晚回家，赶紧检查一下你家的无线摄像头！千万别让几百块买来的“看家神器...",
    "href": "https://www.toutiao.com/w/1849602563009536/",
    "type": "weitoutiao"
  },
  {
    "text": "紧急提醒：今晚回家，一定要和全家人定个“救命暗号”！\n根据最近央视报道，如果你的...",
    "href": "https://www.toutiao.com/w/1849211240362187/",
    "type": "weitoutiao"
  },
  {
    "text": "别再原地热车了！修车师傅看着你满积碳的发动机，嘴都笑歪了！还有那个开暖风除雾的“...",
    "href": "https://www.toutiao.com/w/1849150482805763/",
    "type": "weitoutiao"
  },
  {
    "text": "手机快充到底伤不伤电池？\n估计不少人心里都犯嘀咕：为了充电快那么一小时，把几千块...",
    "href": "https://www.toutiao.com/w/1848397138975872/",
    "type": "weitoutiao"
  }
]